extra_input/__init__.py
extra_input/selectingInputs.py
extra_input/specializedInputs.py
extra_input-1.0.6.dist-info/METADATA
extra_input-1.0.6.dist-info/WHEEL
extra_input-1.0.6.dist-info/top_level.txt
extra_input-1.0.6.dist-info/RECORD
