Metadata-Version: 2.4
Name: extra_input
Version: 1.0.6
Summary: Various functions to get input from the user
Author-email: trinary <lpowyt3@gmail.com>
Classifier: Programming Language :: Python
Classifier: Programming Language :: Python :: 3
Requires-Dist: roman
